segment_lidar/__init__.py
segment_lidar/samlidar.py
segment_lidar/view.py
segment_lidar-0.2.1.dist-info/LICENSE
segment_lidar-0.2.1.dist-info/METADATA
segment_lidar-0.2.1.dist-info/WHEEL
segment_lidar-0.2.1.dist-info/top_level.txt
segment_lidar-0.2.1.dist-info/RECORD
