Metadata-Version: 2.1
Name: segment-lidar
Version: 0.2.1
Summary: A package for segmenting LiDAR data using Segment-Anything Model (SAM) from Meta AI Research.
Home-page: https://github.com/Yarroudh/segment-lidar
Author: Anass Yarroudh
Author-email: ayarroudh@uliege.be
License: BSD 3-Clause "New" or "Revised" License
Classifier: Programming Language :: Python :: 3
Classifier: License :: OSI Approved :: BSD License
Classifier: Operating System :: OS Independent
License-File: LICENSE
Requires-Dist: pycocotools ==2.0.6
Requires-Dist: click ==8.1.3
Requires-Dist: opencv-python ==4.7.0.72
Requires-Dist: numpy ==1.24.3
Requires-Dist: supervision ==0.8.0
Requires-Dist: segment-geospatial ==0.8.1
Requires-Dist: rasterio ==1.3.7
Requires-Dist: laspy ==2.4.1
Requires-Dist: laszip ==0.2.3
Requires-Dist: cloth-simulation-filter ==1.1.4
Requires-Dist: open3d ==0.17.0
